[{"arid_id": "6894", "County": "47141", "T-Value": "(0.000)", "Coefficient": "-0.250", "Significance": "***", "arid": "9233031", "Zipcode": "38501", "State_id": "47", "Bank_Name": "Regions Bank"}, {"arid_id": "7859", "County": "47141", "T-Value": "(0.000)", "Coefficient": "-0.000", "Significance": "Not Significant", "arid": "7264599244", "Zipcode": "38501", "State_id": "47", "Bank_Name": "Loandepot.com, Llc"}, {"arid_id": "8463", "County": "47141", "T-Value": "(0.000)", "Coefficient": "-0.000", "Significance": "Not Significant", "arid": "7830310268", "Zipcode": "38501", "State_id": "47", "Bank_Name": "Mortgage Investors Group, Inc."}]