[{"arid_id": "456", "County": "48085", "T-Value": "(0.234)", "Coefficient": "0.311", "Significance": "Not Significant", "arid": "31467", "Zipcode": "75370", "State_id": "48", "Bank_Name": "Landmark Bank"}, {"arid_id": "552", "County": "48085", "T-Value": "(0.019)", "Coefficient": "-0.005", "Significance": "Not Significant", "arid": "33121", "Zipcode": "75370", "State_id": "48", "Bank_Name": "First Bank"}, {"arid_id": "587", "County": "48085", "T-Value": "(0.013)", "Coefficient": "0.016", "Significance": "Not Significant", "arid": "34239", "Zipcode": "75370", "State_id": "48", "Bank_Name": "First United Bank And Trust Company"}, {"arid_id": "4789", "County": "48085", "T-Value": "(0.475)", "Coefficient": "-0.500", "Significance": "Not Significant", "arid": "523521", "Zipcode": "75370", "State_id": "48", "Bank_Name": "Digital Federal Credit Union"}, {"arid_id": "5044", "County": "48085", "T-Value": "(0.293)", "Coefficient": "0.667", "Significance": "*", "arid": "560806", "Zipcode": "75370", "State_id": "48", "Bank_Name": "Texans"}, {"arid_id": "5820", "County": "48085", "T-Value": "(0.000)", "Coefficient": "-0.000", "Significance": "Not Significant", "arid": "568505", "Zipcode": "75370", "State_id": "48", "Bank_Name": "Intouch Credit Union"}, {"arid_id": "6238", "County": "48085", "T-Value": "(0.161)", "Coefficient": "0.152", "Significance": "Not Significant", "arid": "1706809", "Zipcode": "75370", "State_id": "48", "Bank_Name": "Colonial Savings, F.a."}, {"arid_id": "6823", "County": "48085", "T-Value": "(0.000)", "Coefficient": "-0.000", "Significance": "Not Significant", "arid": "2878898", "Zipcode": "75370", "State_id": "48", "Bank_Name": "Legacytexas Bank"}, {"arid_id": "6886", "County": "48085", "T-Value": "(0.101)", "Coefficient": "-0.071", "Significance": "Not Significant", "arid": "9146672", "Zipcode": "75370", "State_id": "48", "Bank_Name": "Flagstar Bank, Fsb"}, {"arid_id": "6901", "County": "48085", "T-Value": "(0.214)", "Coefficient": "-0.162", "Significance": "Not Significant", "arid": "9339858", "Zipcode": "75370", "State_id": "48", "Bank_Name": "Bokf, National Association"}, {"arid_id": "6911", "County": "48085", "T-Value": "(0.012)", "Coefficient": "0.030", "Significance": "**", "arid": "9451965", "Zipcode": "75370", "State_id": "48", "Bank_Name": "Wells Fargo Bank, National Association"}, {"arid_id": "6914", "County": "48085", "T-Value": "(0.069)", "Coefficient": "0.054", "Significance": "Not Significant", "arid": "9476810", "Zipcode": "75370", "State_id": "48", "Bank_Name": "Citibank, National Association"}, {"arid_id": "6915", "County": "48085", "T-Value": "(0.036)", "Coefficient": "0.106", "Significance": "**", "arid": "9480228", "Zipcode": "75370", "State_id": "48", "Bank_Name": "Bank Of America, National Association"}, {"arid_id": "6938", "County": "48085", "T-Value": "(0.190)", "Coefficient": "-0.385", "Significance": "*", "arid": "9617677", "Zipcode": "75370", "State_id": "48", "Bank_Name": "Navy Federal Credit Union"}, {"arid_id": "6939", "County": "48085", "T-Value": "(0.233)", "Coefficient": "0.500", "Significance": "*", "arid": "9619877", "Zipcode": "75370", "State_id": "48", "Bank_Name": "Usaa Federal Savings Bank"}, {"arid_id": "6949", "County": "48085", "T-Value": "(0.053)", "Coefficient": "0.100", "Significance": "*", "arid": "9697633", "Zipcode": "75370", "State_id": "48", "Bank_Name": "Bbva Usa"}, {"arid_id": "6962", "County": "48085", "T-Value": "(0.022)", "Coefficient": "0.023", "Significance": "Not Significant", "arid": "9852218", "Zipcode": "75370", "State_id": "48", "Bank_Name": "Jpmorgan Chase Bank, National Association"}, {"arid_id": "6963", "County": "48085", "T-Value": "(0.188)", "Coefficient": "0.400", "Significance": "*", "arid": "9852320", "Zipcode": "75370", "State_id": "48", "Bank_Name": "Truist Bank"}, {"arid_id": "7081", "County": "48085", "T-Value": "(0.020)", "Coefficient": "0.010", "Significance": "Not Significant", "arid": "22888798", "Zipcode": "75370", "State_id": "48", "Bank_Name": "Primelending, A Plainscapital Company"}, {"arid_id": "7205", "County": "48085", "T-Value": "(0.121)", "Coefficient": "0.135", "Significance": "Not Significant", "arid": "92590037", "Zipcode": "75370", "State_id": "48", "Bank_Name": "State Farm Bank, F.s.b."}, {"arid_id": "7208", "County": "48085", "T-Value": "(0.137)", "Coefficient": "0.200", "Significance": "Not Significant", "arid": "92735146", "Zipcode": "75370", "State_id": "48", "Bank_Name": "Tiaa, Fsb"}, {"arid_id": "7229", "County": "48085", "T-Value": "(0.387)", "Coefficient": "-0.400", "Significance": "Not Significant", "arid": "94186591", "Zipcode": "75370", "State_id": "48", "Bank_Name": "Pennymac Loan Services, Llc"}, {"arid_id": "7619", "County": "48085", "T-Value": "(0.115)", "Coefficient": "-0.096", "Significance": "Not Significant", "arid": "7136131491", "Zipcode": "75370", "State_id": "48", "Bank_Name": "Caliber Home Loans, Inc."}, {"arid_id": "7737", "County": "48085", "T-Value": "(0.392)", "Coefficient": "-0.500", "Significance": "Not Significant", "arid": "7208745846", "Zipcode": "75370", "State_id": "48", "Bank_Name": "Carrington Mortgage Services, Llc"}, {"arid_id": "7753", "County": "48085", "T-Value": "(0.413)", "Coefficient": "0.500", "Significance": "Not Significant", "arid": "7223039688", "Zipcode": "75370", "State_id": "48", "Bank_Name": "Freedom Mortgage Corporation"}, {"arid_id": "7771", "County": "48085", "T-Value": "(0.008)", "Coefficient": "-0.011", "Significance": "Not Significant", "arid": "7232470039", "Zipcode": "75370", "State_id": "48", "Bank_Name": "Cardinal Financial Company, Limited Partnership"}, {"arid_id": "7775", "County": "48085", "T-Value": "(0.013)", "Coefficient": "0.036", "Significance": "**", "arid": "7232769131", "Zipcode": "75370", "State_id": "48", "Bank_Name": "Finance Of America Mortgage Llc"}, {"arid_id": "7788", "County": "48085", "T-Value": "(0.000)", "Coefficient": "-0.000", "Significance": "Not Significant", "arid": "7260021318", "Zipcode": "75370", "State_id": "48", "Bank_Name": "Amerisave Mortgage Corporation"}, {"arid_id": "7841", "County": "48085", "T-Value": "(0.010)", "Coefficient": "0.007", "Significance": "Not Significant", "arid": "7263249727", "Zipcode": "75370", "State_id": "48", "Bank_Name": "Highland Homeloans, Llc"}, {"arid_id": "7859", "County": "48085", "T-Value": "(0.040)", "Coefficient": "0.035", "Significance": "Not Significant", "arid": "7264599244", "Zipcode": "75370", "State_id": "48", "Bank_Name": "Loandepot.com, Llc"}, {"arid_id": "7911", "County": "48085", "T-Value": "(0.083)", "Coefficient": "0.032", "Significance": "Not Significant", "arid": "7311060110", "Zipcode": "75370", "State_id": "48", "Bank_Name": "First Equity Mortgage Incorporated"}, {"arid_id": "7928", "County": "48085", "T-Value": "(0.054)", "Coefficient": "0.049", "Significance": "Not Significant", "arid": "7320306914", "Zipcode": "75370", "State_id": "48", "Bank_Name": "Brookhollow Mortgage Services, Ltd"}, {"arid_id": "7991", "County": "48085", "T-Value": "(0.089)", "Coefficient": "-0.091", "Significance": "Not Significant", "arid": "7364327855", "Zipcode": "75370", "State_id": "48", "Bank_Name": "Guaranteed Rate, Inc."}, {"arid_id": "8012", "County": "48085", "T-Value": "(0.087)", "Coefficient": "0.026", "Significance": "Not Significant", "arid": "7382750395", "Zipcode": "75370", "State_id": "48", "Bank_Name": "United Wholesale Mortgage, Llc"}, {"arid_id": "8043", "County": "48085", "T-Value": "(0.294)", "Coefficient": "0.286", "Significance": "Not Significant", "arid": "7411795868", "Zipcode": "75370", "State_id": "48", "Bank_Name": "Ditech Financial Llc"}, {"arid_id": "8046", "County": "48085", "T-Value": "(0.127)", "Coefficient": "0.215", "Significance": "Not Significant", "arid": "7411914032", "Zipcode": "75370", "State_id": "48", "Bank_Name": "Homeservices Lending, Llc"}, {"arid_id": "8060", "County": "48085", "T-Value": "(0.045)", "Coefficient": "0.064", "Significance": "Not Significant", "arid": "7421554181", "Zipcode": "75370", "State_id": "48", "Bank_Name": "Pulte Mortgage Llc"}, {"arid_id": "8139", "County": "48085", "T-Value": "(0.086)", "Coefficient": "-0.054", "Significance": "Not Significant", "arid": "7471809999", "Zipcode": "75370", "State_id": "48", "Bank_Name": "Guild Mortgage Company"}, {"arid_id": "8181", "County": "48085", "T-Value": "(0.013)", "Coefficient": "-0.010", "Significance": "Not Significant", "arid": "7522337558", "Zipcode": "75370", "State_id": "48", "Bank_Name": "Taylor Morrison Home Funding, Llc"}, {"arid_id": "8201", "County": "48085", "T-Value": "(0.022)", "Coefficient": "0.019", "Significance": "Not Significant", "arid": "7542409990", "Zipcode": "75370", "State_id": "48", "Bank_Name": "Dhi Mortgage Company, Ltd."}, {"arid_id": "8380", "County": "48085", "T-Value": "(0.000)", "Coefficient": "-0.000", "Significance": "Not Significant", "arid": "7742508160", "Zipcode": "75370", "State_id": "48", "Bank_Name": "Swbc Mortgage Corporation"}, {"arid_id": "8387", "County": "48085", "T-Value": "(0.012)", "Coefficient": "-0.015", "Significance": "Not Significant", "arid": "7752269700", "Zipcode": "75370", "State_id": "48", "Bank_Name": "Highlands Residential Mortgage, Ltd."}, {"arid_id": "8394", "County": "48085", "T-Value": "(0.010)", "Coefficient": "-0.011", "Significance": "Not Significant", "arid": "7752695327", "Zipcode": "75370", "State_id": "48", "Bank_Name": "Everett Financial, Inc."}, {"arid_id": "8398", "County": "48085", "T-Value": "(0.042)", "Coefficient": "-0.052", "Significance": "Not Significant", "arid": "7752838184", "Zipcode": "75370", "State_id": "48", "Bank_Name": "Ark-la-tex Financial Services, Llc."}, {"arid_id": "8401", "County": "48085", "T-Value": "(0.010)", "Coefficient": "-0.010", "Significance": "Not Significant", "arid": "7752888366", "Zipcode": "75370", "State_id": "48", "Bank_Name": "Lending Partners, Ltd."}, {"arid_id": "8402", "County": "48085", "T-Value": "(0.092)", "Coefficient": "0.186", "Significance": "*", "arid": "7752921540", "Zipcode": "75370", "State_id": "48", "Bank_Name": "Nationstar Mortgage Llc"}, {"arid_id": "8404", "County": "48085", "T-Value": "(0.061)", "Coefficient": "0.060", "Significance": "Not Significant", "arid": "7752945170", "Zipcode": "75370", "State_id": "48", "Bank_Name": "Aspire Financial, Inc."}, {"arid_id": "8407", "County": "48085", "T-Value": "(0.089)", "Coefficient": "-0.077", "Significance": "Not Significant", "arid": "7760236067", "Zipcode": "75370", "State_id": "48", "Bank_Name": "Cornerstone Home Lending, Inc."}, {"arid_id": "8413", "County": "48085", "T-Value": "(0.021)", "Coefficient": "-0.036", "Significance": "Not Significant", "arid": "7760503625", "Zipcode": "75370", "State_id": "48", "Bank_Name": "Fairway Independent Mortgage Corporation"}, {"arid_id": "8577", "County": "48085", "T-Value": "(0.000)", "Coefficient": "0.333", "Significance": "***", "arid": "9133222578", "Zipcode": "75370", "State_id": "48", "Bank_Name": "Citimortgage, Inc."}, {"arid_id": "8758", "County": "48085", "T-Value": "(0.067)", "Coefficient": "-0.007", "Significance": "Not Significant", "arid": "71100900005", "Zipcode": "75370", "State_id": "48", "Bank_Name": "Sfmc, Lp"}, {"arid_id": "8834", "County": "48085", "T-Value": "(0.037)", "Coefficient": "0.067", "Significance": "Not Significant", "arid": "72149009991", "Zipcode": "75370", "State_id": "48", "Bank_Name": "Eagle Home Mortgage, Llc"}, {"arid_id": "8845", "County": "48085", "T-Value": "(0.051)", "Coefficient": "0.180", "Significance": "***", "arid": "73000809992", "Zipcode": "75370", "State_id": "48", "Bank_Name": "K. Hovnanian American Mortgage, L.l.c."}, {"arid_id": "8903", "County": "48085", "T-Value": "(0.043)", "Coefficient": "-0.024", "Significance": "Not Significant", "arid": "77197000003", "Zipcode": "75370", "State_id": "48", "Bank_Name": "Quicken Loans, Llc"}, {"arid_id": "8914", "County": "48085", "T-Value": "(0.134)", "Coefficient": "0.107", "Significance": "Not Significant", "arid": "77275700004", "Zipcode": "75370", "State_id": "48", "Bank_Name": "Tbi Mortgage Company"}, {"arid_id": "8966", "County": "48085", "T-Value": "(0.145)", "Coefficient": "0.155", "Significance": "Not Significant", "arid": "77810600004", "Zipcode": "75370", "State_id": "48", "Bank_Name": "Provident Funding Associates, L.p."}]