[{"arid_id": "1617", "County": "12061", "T-Value": "(0.102)", "Coefficient": "-0.286", "Significance": "**", "arid": "114838", "Zipcode": "32962", "State_id": "12", "Bank_Name": "Seacoast National Bank"}, {"arid_id": "6911", "County": "12061", "T-Value": "(0.046)", "Coefficient": "0.037", "Significance": "Not Significant", "arid": "9451965", "Zipcode": "32962", "State_id": "12", "Bank_Name": "Wells Fargo Bank, National Association"}, {"arid_id": "6915", "County": "12061", "T-Value": "(0.112)", "Coefficient": "-0.400", "Significance": "***", "arid": "9480228", "Zipcode": "32962", "State_id": "12", "Bank_Name": "Bank Of America, National Association"}, {"arid_id": "6960", "County": "12061", "T-Value": "(0.104)", "Coefficient": "0.245", "Significance": "**", "arid": "9817824", "Zipcode": "32962", "State_id": "12", "Bank_Name": "Pnc Bank, National Association"}, {"arid_id": "6962", "County": "12061", "T-Value": "(0.059)", "Coefficient": "0.210", "Significance": "***", "arid": "9852218", "Zipcode": "32962", "State_id": "12", "Bank_Name": "Jpmorgan Chase Bank, National Association"}, {"arid_id": "7619", "County": "12061", "T-Value": "(0.145)", "Coefficient": "0.377", "Significance": "**", "arid": "7136131491", "Zipcode": "32962", "State_id": "12", "Bank_Name": "Caliber Home Loans, Inc."}, {"arid_id": "7690", "County": "12061", "T-Value": "(0.257)", "Coefficient": "0.400", "Significance": "Not Significant", "arid": "7203702275", "Zipcode": "32962", "State_id": "12", "Bank_Name": "Fbc Mortgage, Llc"}, {"arid_id": "7859", "County": "12061", "T-Value": "(0.184)", "Coefficient": "-0.025", "Significance": "Not Significant", "arid": "7264599244", "Zipcode": "32962", "State_id": "12", "Bank_Name": "Loandepot.com, Llc"}, {"arid_id": "8402", "County": "12061", "T-Value": "(0.000)", "Coefficient": "-0.000", "Significance": "Not Significant", "arid": "7752921540", "Zipcode": "32962", "State_id": "12", "Bank_Name": "Nationstar Mortgage Llc"}, {"arid_id": "8834", "County": "12061", "T-Value": "(0.104)", "Coefficient": "0.158", "Significance": "Not Significant", "arid": "72149009991", "Zipcode": "32962", "State_id": "12", "Bank_Name": "Eagle Home Mortgage, Llc"}, {"arid_id": "8903", "County": "12061", "T-Value": "(0.185)", "Coefficient": "0.078", "Significance": "Not Significant", "arid": "77197000003", "Zipcode": "32962", "State_id": "12", "Bank_Name": "Quicken Loans, Llc"}, {"arid_id": "8910", "County": "12061", "T-Value": "(0.041)", "Coefficient": "0.041", "Significance": "Not Significant", "arid": "77257500009", "Zipcode": "32962", "State_id": "12", "Bank_Name": "Academy Mortgage Corporation"}]