[{"arid_id": "1334", "County": "25027", "T-Value": "(0.052)", "Coefficient": "0.048", "Significance": "Not Significant", "arid": "58218", "Zipcode": "01453", "State_id": "25", "Bank_Name": "Central One Federal Credit Union"}, {"arid_id": "1872", "County": "25027", "T-Value": "(0.032)", "Coefficient": "-0.029", "Significance": "Not Significant", "arid": "124131", "Zipcode": "01453", "State_id": "25", "Bank_Name": "Leader Bank, National Association"}, {"arid_id": "3184", "County": "25027", "T-Value": "(0.186)", "Coefficient": "2.000", "Significance": "***", "arid": "326451", "Zipcode": "01453", "State_id": "25", "Bank_Name": "Fidelity Co-operative Bank"}, {"arid_id": "4326", "County": "25027", "T-Value": "(0.011)", "Coefficient": "0.012", "Significance": "Not Significant", "arid": "390175", "Zipcode": "01453", "State_id": "25", "Bank_Name": "The Bank Of Canton"}, {"arid_id": "4328", "County": "25027", "T-Value": "(0.251)", "Coefficient": "-0.500", "Significance": "*", "arid": "390181", "Zipcode": "01453", "State_id": "25", "Bank_Name": "Clinton Savings Bank"}, {"arid_id": "4355", "County": "25027", "T-Value": "(0.042)", "Coefficient": "-0.007", "Significance": "Not Significant", "arid": "390290", "Zipcode": "01453", "State_id": "25", "Bank_Name": "Unibank For Savings"}, {"arid_id": "4789", "County": "25027", "T-Value": "(0.061)", "Coefficient": "0.049", "Significance": "Not Significant", "arid": "523521", "Zipcode": "01453", "State_id": "25", "Bank_Name": "Digital Federal Credit Union"}, {"arid_id": "4821", "County": "25027", "T-Value": "(0.044)", "Coefficient": "0.085", "Significance": "*", "arid": "524250", "Zipcode": "01453", "State_id": "25", "Bank_Name": "Ic Federal Credit Union"}, {"arid_id": "5458", "County": "25027", "T-Value": "(0.166)", "Coefficient": "0.124", "Significance": "Not Significant", "arid": "566479", "Zipcode": "01453", "State_id": "25", "Bank_Name": "Workers Credit Union"}, {"arid_id": "5478", "County": "25027", "T-Value": "(0.168)", "Coefficient": "-0.022", "Significance": "Not Significant", "arid": "566699", "Zipcode": "01453", "State_id": "25", "Bank_Name": "Leominster Credit Union"}, {"arid_id": "5676", "County": "25027", "T-Value": "(0.000)", "Coefficient": "-0.000", "Significance": "Not Significant", "arid": "568057", "Zipcode": "01453", "State_id": "25", "Bank_Name": "Homefield"}, {"arid_id": "6137", "County": "25027", "T-Value": "(0.176)", "Coefficient": "0.316", "Significance": "Not Significant", "arid": "1704167", "Zipcode": "01453", "State_id": "25", "Bank_Name": "Milford Federal Bank"}, {"arid_id": "6911", "County": "25027", "T-Value": "(0.045)", "Coefficient": "-0.035", "Significance": "Not Significant", "arid": "9451965", "Zipcode": "01453", "State_id": "25", "Bank_Name": "Wells Fargo Bank, National Association"}, {"arid_id": "6915", "County": "25027", "T-Value": "(0.060)", "Coefficient": "-0.247", "Significance": "***", "arid": "9480228", "Zipcode": "01453", "State_id": "25", "Bank_Name": "Bank Of America, National Association"}, {"arid_id": "6951", "County": "25027", "T-Value": "(0.180)", "Coefficient": "0.203", "Significance": "Not Significant", "arid": "9722777", "Zipcode": "01453", "State_id": "25", "Bank_Name": "Santander Bank, N.a."}, {"arid_id": "6962", "County": "25027", "T-Value": "(0.115)", "Coefficient": "-0.206", "Significance": "Not Significant", "arid": "9852218", "Zipcode": "01453", "State_id": "25", "Bank_Name": "Jpmorgan Chase Bank, National Association"}, {"arid_id": "7221", "County": "25027", "T-Value": "(0.000)", "Coefficient": "-0.000", "Significance": "Not Significant", "arid": "93303298", "Zipcode": "01453", "State_id": "25", "Bank_Name": "Citizens Bank, National Association"}, {"arid_id": "7239", "County": "25027", "T-Value": "(0.054)", "Coefficient": "-0.106", "Significance": "*", "arid": "710464609", "Zipcode": "01453", "State_id": "25", "Bank_Name": "Residential Mortgage Services, Inc."}, {"arid_id": "7753", "County": "25027", "T-Value": "(0.000)", "Coefficient": "0.500", "Significance": "***", "arid": "7223039688", "Zipcode": "01453", "State_id": "25", "Bank_Name": "Freedom Mortgage Corporation"}, {"arid_id": "7788", "County": "25027", "T-Value": "(0.000)", "Coefficient": "-0.000", "Significance": "Not Significant", "arid": "7260021318", "Zipcode": "01453", "State_id": "25", "Bank_Name": "Amerisave Mortgage Corporation"}, {"arid_id": "7859", "County": "25027", "T-Value": "(0.110)", "Coefficient": "-0.111", "Significance": "Not Significant", "arid": "7264599244", "Zipcode": "01453", "State_id": "25", "Bank_Name": "Loandepot.com, Llc"}, {"arid_id": "7991", "County": "25027", "T-Value": "(0.015)", "Coefficient": "-0.002", "Significance": "Not Significant", "arid": "7364327855", "Zipcode": "01453", "State_id": "25", "Bank_Name": "Guaranteed Rate, Inc."}, {"arid_id": "8012", "County": "25027", "T-Value": "(0.176)", "Coefficient": "0.103", "Significance": "Not Significant", "arid": "7382750395", "Zipcode": "01453", "State_id": "25", "Bank_Name": "United Wholesale Mortgage, Llc"}, {"arid_id": "8043", "County": "25027", "T-Value": "(0.000)", "Coefficient": "-0.000", "Significance": "Not Significant", "arid": "7411795868", "Zipcode": "01453", "State_id": "25", "Bank_Name": "Ditech Financial Llc"}, {"arid_id": "8413", "County": "25027", "T-Value": "(0.036)", "Coefficient": "0.011", "Significance": "Not Significant", "arid": "7760503625", "Zipcode": "01453", "State_id": "25", "Bank_Name": "Fairway Independent Mortgage Corporation"}, {"arid_id": "8903", "County": "25027", "T-Value": "(0.054)", "Coefficient": "-0.088", "Significance": "Not Significant", "arid": "77197000003", "Zipcode": "01453", "State_id": "25", "Bank_Name": "Quicken Loans, Llc"}, {"arid_id": "8914", "County": "25027", "T-Value": "(0.301)", "Coefficient": "0.300", "Significance": "Not Significant", "arid": "77275700004", "Zipcode": "01453", "State_id": "25", "Bank_Name": "Tbi Mortgage Company"}]