[
    {
        "arid_id": 5961,
        "County": 39151,
        "T-Value": "(0.046)",
        "Coefficient": 0.209,
        "Significance": "***",
        "arid": 912311,
        "rssdid": 12311.0,
        "Zipcode": "44647",
        "State_id": 39.0,
        "Bank_Name": "The Huntington National Bank"
    },
    {
        "arid_id": 6898,
        "County": 39151,
        "T-Value": "(0.143)",
        "Coefficient": -0.244,
        "Significance": "Not Significant",
        "arid": 9280110,
        "rssdid": 280110.0,
        "Zipcode": "44647",
        "State_id": 39.0,
        "Bank_Name": "Keybank National Association"
    },
    {
        "arid_id": 6911,
        "County": 39151,
        "T-Value": "(0.089)",
        "Coefficient": 0.125,
        "Significance": "Not Significant",
        "arid": 9451965,
        "rssdid": 451965.0,
        "Zipcode": "44647",
        "State_id": 39.0,
        "Bank_Name": "Wells Fargo Bank, National Association"
    },
    {
        "arid_id": 6914,
        "County": 39151,
        "T-Value": "(0.203)",
        "Coefficient": -1.333,
        "Significance": "***",
        "arid": 9476810,
        "rssdid": 476810.0,
        "Zipcode": "44647",
        "State_id": 39.0,
        "Bank_Name": "Citibank, National Association"
    },
    {
        "arid_id": 6960,
        "County": 39151,
        "T-Value": "(0.162)",
        "Coefficient": 0.5,
        "Significance": "**",
        "arid": 9817824,
        "rssdid": 817824.0,
        "Zipcode": "44647",
        "State_id": 39.0,
        "Bank_Name": "Pnc Bank, National Association"
    },
    {
        "arid_id": 6962,
        "County": 39151,
        "T-Value": "(0.039)",
        "Coefficient": -0.019,
        "Significance": "Not Significant",
        "arid": 9852218,
        "rssdid": 852218.0,
        "Zipcode": "44647",
        "State_id": 39.0,
        "Bank_Name": "Jpmorgan Chase Bank, National Association"
    },
    {
        "arid_id": 7207,
        "County": 39151,
        "T-Value": "(0.000)",
        "Coefficient": 0.0,
        "Significance": "Not Significant",
        "arid": 92712969,
        "rssdid": 2712969.0,
        "Zipcode": "44647",
        "State_id": 39.0,
        "Bank_Name": "Fifth Third Mortgage Company"
    },
    {
        "arid_id": 7221,
        "County": 39151,
        "T-Value": "(0.241)",
        "Coefficient": -0.22,
        "Significance": "Not Significant",
        "arid": 93303298,
        "rssdid": 3303298.0,
        "Zipcode": "44647",
        "State_id": 39.0,
        "Bank_Name": "Citizens Bank, National Association"
    },
    {
        "arid_id": 8903,
        "County": 39151,
        "T-Value": "(0.179)",
        "Coefficient": 0.043,
        "Significance": "Not Significant",
        "arid": 77197000003,
        "rssdid": 3870679.0,
        "Zipcode": "44647",
        "State_id": 39.0,
        "Bank_Name": "Quicken Loans, LLC"
    }
]