[
    {
        "arid_id": 1262,
        "County": 42077,
        "T-Value": "(0.108)",
        "Coefficient": -0.25,
        "Significance": "**",
        "arid": 56885,
        "rssdid": 335382.0,
        "Zipcode": "18034",
        "State_id": 42.0,
        "Bank_Name": "People First"
    },
    {
        "arid_id": 1416,
        "County": 42077,
        "T-Value": "(0.000)",
        "Coefficient": 0.0,
        "Significance": "Not Significant",
        "arid": 59607,
        "rssdid": 84989.0,
        "Zipcode": "18034",
        "State_id": 42.0,
        "Bank_Name": "Apci Federal Credit Union"
    },
    {
        "arid_id": 6432,
        "County": 42077,
        "T-Value": "(0.000)",
        "Coefficient": 0.0,
        "Significance": "Not Significant",
        "arid": 2140018,
        "rssdid": 140018.0,
        "Zipcode": "18034",
        "State_id": 42.0,
        "Bank_Name": "Lafayette Ambassador Bank"
    },
    {
        "arid_id": 6911,
        "County": 42077,
        "T-Value": "(0.032)",
        "Coefficient": 0.085,
        "Significance": "**",
        "arid": 9451965,
        "rssdid": 451965.0,
        "Zipcode": "18034",
        "State_id": 42.0,
        "Bank_Name": "Wells Fargo Bank, National Association"
    },
    {
        "arid_id": 6914,
        "County": 42077,
        "T-Value": "(0.000)",
        "Coefficient": 0.0,
        "Significance": "Not Significant",
        "arid": 9476810,
        "rssdid": 476810.0,
        "Zipcode": "18034",
        "State_id": 42.0,
        "Bank_Name": "Citibank, National Association"
    },
    {
        "arid_id": 6915,
        "County": 42077,
        "T-Value": "(0.228)",
        "Coefficient": -0.159,
        "Significance": "Not Significant",
        "arid": 9480228,
        "rssdid": 480228.0,
        "Zipcode": "18034",
        "State_id": 42.0,
        "Bank_Name": "Bank of America, National Association"
    },
    {
        "arid_id": 6960,
        "County": 42077,
        "T-Value": "(0.207)",
        "Coefficient": 0.5,
        "Significance": "**",
        "arid": 9817824,
        "rssdid": 817824.0,
        "Zipcode": "18034",
        "State_id": 42.0,
        "Bank_Name": "Pnc Bank, National Association"
    },
    {
        "arid_id": 6962,
        "County": 42077,
        "T-Value": "(0.245)",
        "Coefficient": 0.286,
        "Significance": "Not Significant",
        "arid": 9852218,
        "rssdid": 852218.0,
        "Zipcode": "18034",
        "State_id": 42.0,
        "Bank_Name": "Jpmorgan Chase Bank, National Association"
    },
    {
        "arid_id": 6963,
        "County": 42077,
        "T-Value": "(0.228)",
        "Coefficient": -0.5,
        "Significance": "*",
        "arid": 9852320,
        "rssdid": 852320.0,
        "Zipcode": "18034",
        "State_id": 42.0,
        "Bank_Name": "Truist Bank"
    },
    {
        "arid_id": 7619,
        "County": 42077,
        "T-Value": "(0.436)",
        "Coefficient": -0.5,
        "Significance": "Not Significant",
        "arid": 7136131491,
        "rssdid": 3871519.0,
        "Zipcode": "18034",
        "State_id": 42.0,
        "Bank_Name": "Caliber Home Loans, INC."
    },
    {
        "arid_id": 7642,
        "County": 42077,
        "T-Value": "(0.109)",
        "Coefficient": 0.163,
        "Significance": "Not Significant",
        "arid": 7200378305,
        "rssdid": 3885794.0,
        "Zipcode": "18034",
        "State_id": 42.0,
        "Bank_Name": "Trident Mortgage Company LP"
    },
    {
        "arid_id": 7859,
        "County": 42077,
        "T-Value": "(0.160)",
        "Coefficient": 0.333,
        "Significance": "*",
        "arid": 7264599244,
        "rssdid": 4438209.0,
        "Zipcode": "18034",
        "State_id": 42.0,
        "Bank_Name": "Loandepot.com, LLC"
    },
    {
        "arid_id": 7885,
        "County": 42077,
        "T-Value": "(0.185)",
        "Coefficient": -0.301,
        "Significance": "Not Significant",
        "arid": 7272389039,
        "rssdid": 4437873.0,
        "Zipcode": "18034",
        "State_id": 42.0,
        "Bank_Name": "American Neighborhood Mortgage Acceptance Company LLC"
    },
    {
        "arid_id": 8402,
        "County": 42077,
        "T-Value": "(0.295)",
        "Coefficient": 0.4,
        "Significance": "Not Significant",
        "arid": 7752921540,
        "rssdid": 3845828.0,
        "Zipcode": "18034",
        "State_id": 42.0,
        "Bank_Name": "Nationstar Mortgage LLC"
    },
    {
        "arid_id": 8903,
        "County": 42077,
        "T-Value": "(0.449)",
        "Coefficient": -0.5,
        "Significance": "Not Significant",
        "arid": 77197000003,
        "rssdid": 3870679.0,
        "Zipcode": "18034",
        "State_id": 42.0,
        "Bank_Name": "Quicken Loans, LLC"
    },
    {
        "arid_id": 8914,
        "County": 42077,
        "T-Value": "(0.469)",
        "Coefficient": 0.364,
        "Significance": "Not Significant",
        "arid": 77275700004,
        "rssdid": 3885806.0,
        "Zipcode": "18034",
        "State_id": 42.0,
        "Bank_Name": "TBI Mortgage Company"
    }
]