[
    {
        "arid_id": 1299,
        "County": 26049,
        "T-Value": "(0.056)",
        "Coefficient": 0.077,
        "Significance": "Not Significant",
        "arid": 57569,
        "rssdid": 218887.0,
        "Zipcode": "48463",
        "State_id": 26.0,
        "Bank_Name": "Dort Financial Credit Union"
    },
    {
        "arid_id": 5142,
        "County": 26049,
        "T-Value": "(0.132)",
        "Coefficient": 0.272,
        "Significance": "*",
        "arid": 561797,
        "rssdid": 697594.0,
        "Zipcode": "48463",
        "State_id": 26.0,
        "Bank_Name": "Elga Credit Union"
    },
    {
        "arid_id": 5205,
        "County": 26049,
        "T-Value": "(0.288)",
        "Coefficient": -0.368,
        "Significance": "Not Significant",
        "arid": 562514,
        "rssdid": 651596.0,
        "Zipcode": "48463",
        "State_id": 26.0,
        "Bank_Name": "Lake Michigan Credit Union"
    },
    {
        "arid_id": 5902,
        "County": 26049,
        "T-Value": "(0.154)",
        "Coefficient": -0.077,
        "Significance": "Not Significant",
        "arid": 568646,
        "rssdid": 420989.0,
        "Zipcode": "48463",
        "State_id": 26.0,
        "Bank_Name": "Financial Plus Credit Union"
    },
    {
        "arid_id": 5961,
        "County": 26049,
        "T-Value": "(0.000)",
        "Coefficient": 0.0,
        "Significance": "Not Significant",
        "arid": 912311,
        "rssdid": 12311.0,
        "Zipcode": "48463",
        "State_id": 26.0,
        "Bank_Name": "The Huntington National Bank"
    },
    {
        "arid_id": 6911,
        "County": 26049,
        "T-Value": "(0.219)",
        "Coefficient": 0.364,
        "Significance": "Not Significant",
        "arid": 9451965,
        "rssdid": 451965.0,
        "Zipcode": "48463",
        "State_id": 26.0,
        "Bank_Name": "Wells Fargo Bank, National Association"
    },
    {
        "arid_id": 6914,
        "County": 26049,
        "T-Value": "(0.000)",
        "Coefficient": 0.5,
        "Significance": "***",
        "arid": 9476810,
        "rssdid": 476810.0,
        "Zipcode": "48463",
        "State_id": 26.0,
        "Bank_Name": "Citibank, National Association"
    },
    {
        "arid_id": 6915,
        "County": 26049,
        "T-Value": "(0.681)",
        "Coefficient": -0.067,
        "Significance": "Not Significant",
        "arid": 9480228,
        "rssdid": 480228.0,
        "Zipcode": "48463",
        "State_id": 26.0,
        "Bank_Name": "Bank of America, National Association"
    },
    {
        "arid_id": 6962,
        "County": 26049,
        "T-Value": "(0.097)",
        "Coefficient": 0.076,
        "Significance": "Not Significant",
        "arid": 9852218,
        "rssdid": 852218.0,
        "Zipcode": "48463",
        "State_id": 26.0,
        "Bank_Name": "Jpmorgan Chase Bank, National Association"
    },
    {
        "arid_id": 7216,
        "County": 26049,
        "T-Value": "(1.468)",
        "Coefficient": -41.595,
        "Significance": "***",
        "arid": 93072606,
        "rssdid": 3072606.0,
        "Zipcode": "48463",
        "State_id": 26.0,
        "Bank_Name": "Fifth Third Mortgage-mi, LLC"
    },
    {
        "arid_id": 8020,
        "County": 26049,
        "T-Value": "(0.020)",
        "Coefficient": 0.017,
        "Significance": "Not Significant",
        "arid": 7383434023,
        "rssdid": 4325541.0,
        "Zipcode": "48463",
        "State_id": 26.0,
        "Bank_Name": "J. Virgil, INC."
    },
    {
        "arid_id": 8043,
        "County": 26049,
        "T-Value": "(0.326)",
        "Coefficient": 0.5,
        "Significance": "Not Significant",
        "arid": 7411795868,
        "rssdid": 3861163.0,
        "Zipcode": "48463",
        "State_id": 26.0,
        "Bank_Name": "Ditech Financial LLC"
    },
    {
        "arid_id": 8402,
        "County": 26049,
        "T-Value": "(0.262)",
        "Coefficient": 0.308,
        "Significance": "Not Significant",
        "arid": 7752921540,
        "rssdid": 3845828.0,
        "Zipcode": "48463",
        "State_id": 26.0,
        "Bank_Name": "Nationstar Mortgage LLC"
    },
    {
        "arid_id": 8903,
        "County": 26049,
        "T-Value": "(0.089)",
        "Coefficient": -0.031,
        "Significance": "Not Significant",
        "arid": 77197000003,
        "rssdid": 3870679.0,
        "Zipcode": "48463",
        "State_id": 26.0,
        "Bank_Name": "Quicken Loans, LLC"
    }
]