[
    {
        "arid_id": 1344,
        "County": 16005,
        "T-Value": "(0.112)",
        "Coefficient": 0.388,
        "Significance": "***",
        "arid": 58428,
        "rssdid": 593687.0,
        "Zipcode": "83202",
        "State_id": 16.0,
        "Bank_Name": "Advantage Plus"
    },
    {
        "arid_id": 2202,
        "County": 16005,
        "T-Value": "(0.000)",
        "Coefficient": 0.5,
        "Significance": "***",
        "arid": 311666,
        "rssdid": 543262.0,
        "Zipcode": "83202",
        "State_id": 16.0,
        "Bank_Name": "D. L. Evans Bank"
    },
    {
        "arid_id": 3471,
        "County": 16005,
        "T-Value": "(0.012)",
        "Coefficient": 0.102,
        "Significance": "***",
        "arid": 330788,
        "rssdid": 2634191.0,
        "Zipcode": "83202",
        "State_id": 16.0,
        "Bank_Name": "Glacier Bank"
    },
    {
        "arid_id": 4898,
        "County": 16005,
        "T-Value": "(0.000)",
        "Coefficient": 0.0,
        "Significance": "Not Significant",
        "arid": 524692,
        "rssdid": 611198.0,
        "Zipcode": "83202",
        "State_id": 16.0,
        "Bank_Name": "Mountain America"
    },
    {
        "arid_id": 5265,
        "County": 16005,
        "T-Value": "(0.042)",
        "Coefficient": 0.069,
        "Significance": "Not Significant",
        "arid": 563194,
        "rssdid": 322793.0,
        "Zipcode": "83202",
        "State_id": 16.0,
        "Bank_Name": "Idaho Central"
    },
    {
        "arid_id": 5743,
        "County": 16005,
        "T-Value": "(0.000)",
        "Coefficient": 0.0,
        "Significance": "Not Significant",
        "arid": 568353,
        "rssdid": 478494.0,
        "Zipcode": "83202",
        "State_id": 16.0,
        "Bank_Name": "Westmark Credit Union"
    },
    {
        "arid_id": 6911,
        "County": 16005,
        "T-Value": "(0.000)",
        "Coefficient": 0.0,
        "Significance": "Not Significant",
        "arid": 9451965,
        "rssdid": 451965.0,
        "Zipcode": "83202",
        "State_id": 16.0,
        "Bank_Name": "Wells Fargo Bank, National Association"
    },
    {
        "arid_id": 8402,
        "County": 16005,
        "T-Value": "(0.000)",
        "Coefficient": 0.333,
        "Significance": "***",
        "arid": 7752921540,
        "rssdid": 3845828.0,
        "Zipcode": "83202",
        "State_id": 16.0,
        "Bank_Name": "Nationstar Mortgage LLC"
    }
]