[
    {
        "arid_id": 6911,
        "County": 6009,
        "T-Value": "(0.069)",
        "Coefficient": -0.128,
        "Significance": "*",
        "arid": 9451965,
        "rssdid": 451965.0,
        "Zipcode": "95222",
        "State_id": 6.0,
        "Bank_Name": "Wells Fargo Bank, National Association"
    },
    {
        "arid_id": 6915,
        "County": 6009,
        "T-Value": "(0.149)",
        "Coefficient": -0.5,
        "Significance": "**",
        "arid": 9480228,
        "rssdid": 480228.0,
        "Zipcode": "95222",
        "State_id": 6.0,
        "Bank_Name": "Bank of America, National Association"
    },
    {
        "arid_id": 7859,
        "County": 6009,
        "T-Value": "(0.000)",
        "Coefficient": 0.0,
        "Significance": "Not Significant",
        "arid": 7264599244,
        "rssdid": 4438209.0,
        "Zipcode": "95222",
        "State_id": 6.0,
        "Bank_Name": "Loandepot.com, LLC"
    },
    {
        "arid_id": 8903,
        "County": 6009,
        "T-Value": "(0.000)",
        "Coefficient": 0.0,
        "Significance": "Not Significant",
        "arid": 77197000003,
        "rssdid": 3870679.0,
        "Zipcode": "95222",
        "State_id": 6.0,
        "Bank_Name": "Quicken Loans, LLC"
    }
]