[
    {
        "arid_id": 567,
        "County": 17031,
        "T-Value": "(0.223)",
        "Coefficient": 0.277,
        "Significance": "Not Significant",
        "arid": 33657,
        "rssdid": 850036.0,
        "Zipcode": "60090",
        "State_id": 17.0,
        "Bank_Name": "First American Bank"
    },
    {
        "arid_id": 1808,
        "County": 17031,
        "T-Value": "(0.013)",
        "Coefficient": 0.046,
        "Significance": "***",
        "arid": 123216,
        "rssdid": 2508751.0,
        "Zipcode": "60090",
        "State_id": 17.0,
        "Bank_Name": "Barrington Bank & Trust Company, N.A."
    },
    {
        "arid_id": 5106,
        "County": 17031,
        "T-Value": "(0.471)",
        "Coefficient": 0.5,
        "Significance": "Not Significant",
        "arid": 561447,
        "rssdid": 52193.0,
        "Zipcode": "60090",
        "State_id": 17.0,
        "Bank_Name": "Numark Credit Union"
    },
    {
        "arid_id": 5662,
        "County": 17031,
        "T-Value": "(0.104)",
        "Coefficient": 0.036,
        "Significance": "Not Significant",
        "arid": 567955,
        "rssdid": 367392.0,
        "Zipcode": "60090",
        "State_id": 17.0,
        "Bank_Name": "Alliant Credit Union"
    },
    {
        "arid_id": 5961,
        "County": 17031,
        "T-Value": "(0.061)",
        "Coefficient": -0.098,
        "Significance": "Not Significant",
        "arid": 912311,
        "rssdid": 12311.0,
        "Zipcode": "60090",
        "State_id": 17.0,
        "Bank_Name": "The Huntington National Bank"
    },
    {
        "arid_id": 5968,
        "County": 17031,
        "T-Value": "(0.041)",
        "Coefficient": 0.146,
        "Significance": "***",
        "arid": 975633,
        "rssdid": 75633.0,
        "Zipcode": "60090",
        "State_id": 17.0,
        "Bank_Name": "Bmo Harris Bank National Association"
    },
    {
        "arid_id": 6739,
        "County": 17031,
        "T-Value": "(0.047)",
        "Coefficient": -0.014,
        "Significance": "Not Significant",
        "arid": 2716833,
        "rssdid": 716833.0,
        "Zipcode": "60090",
        "State_id": 17.0,
        "Bank_Name": "Marquette Bank"
    },
    {
        "arid_id": 6886,
        "County": 17031,
        "T-Value": "(0.111)",
        "Coefficient": -0.169,
        "Significance": "Not Significant",
        "arid": 9146672,
        "rssdid": 146672.0,
        "Zipcode": "60090",
        "State_id": 17.0,
        "Bank_Name": "Flagstar Bank, FSB"
    },
    {
        "arid_id": 6890,
        "County": 17031,
        "T-Value": "(0.450)",
        "Coefficient": 0.444,
        "Significance": "Not Significant",
        "arid": 9210434,
        "rssdid": 210434.0,
        "Zipcode": "60090",
        "State_id": 17.0,
        "Bank_Name": "The Northern Trust Company"
    },
    {
        "arid_id": 6911,
        "County": 17031,
        "T-Value": "(0.009)",
        "Coefficient": 0.048,
        "Significance": "***",
        "arid": 9451965,
        "rssdid": 451965.0,
        "Zipcode": "60090",
        "State_id": 17.0,
        "Bank_Name": "Wells Fargo Bank, National Association"
    },
    {
        "arid_id": 6914,
        "County": 17031,
        "T-Value": "(0.026)",
        "Coefficient": -0.004,
        "Significance": "Not Significant",
        "arid": 9476810,
        "rssdid": 476810.0,
        "Zipcode": "60090",
        "State_id": 17.0,
        "Bank_Name": "Citibank, National Association"
    },
    {
        "arid_id": 6915,
        "County": 17031,
        "T-Value": "(0.022)",
        "Coefficient": 0.044,
        "Significance": "*",
        "arid": 9480228,
        "rssdid": 480228.0,
        "Zipcode": "60090",
        "State_id": 17.0,
        "Bank_Name": "Bank of America, National Association"
    },
    {
        "arid_id": 6921,
        "County": 17031,
        "T-Value": "(0.019)",
        "Coefficient": 0.144,
        "Significance": "***",
        "arid": 9504713,
        "rssdid": 504713.0,
        "Zipcode": "60090",
        "State_id": 17.0,
        "Bank_Name": "U.S. Bank National Association"
    },
    {
        "arid_id": 6941,
        "County": 17031,
        "T-Value": "(0.039)",
        "Coefficient": -0.05,
        "Significance": "Not Significant",
        "arid": 9656733,
        "rssdid": 656733.0,
        "Zipcode": "60090",
        "State_id": 17.0,
        "Bank_Name": "Mb Financial Bank, National Association"
    },
    {
        "arid_id": 6952,
        "County": 17031,
        "T-Value": "(0.056)",
        "Coefficient": -0.23,
        "Significance": "***",
        "arid": 9723112,
        "rssdid": 723112.0,
        "Zipcode": "60090",
        "State_id": 17.0,
        "Bank_Name": "Fifth Third Bank, National Association"
    },
    {
        "arid_id": 6960,
        "County": 17031,
        "T-Value": "(0.024)",
        "Coefficient": 0.082,
        "Significance": "***",
        "arid": 9817824,
        "rssdid": 817824.0,
        "Zipcode": "60090",
        "State_id": 17.0,
        "Bank_Name": "Pnc Bank, National Association"
    },
    {
        "arid_id": 6962,
        "County": 17031,
        "T-Value": "(0.007)",
        "Coefficient": 0.031,
        "Significance": "***",
        "arid": 9852218,
        "rssdid": 852218.0,
        "Zipcode": "60090",
        "State_id": 17.0,
        "Bank_Name": "Jpmorgan Chase Bank, National Association"
    },
    {
        "arid_id": 6967,
        "County": 17031,
        "T-Value": "(0.024)",
        "Coefficient": 0.027,
        "Significance": "Not Significant",
        "arid": 9917742,
        "rssdid": 917742.0,
        "Zipcode": "60090",
        "State_id": 17.0,
        "Bank_Name": "Associated Bank, National Association"
    },
    {
        "arid_id": 7015,
        "County": 17031,
        "T-Value": "(0.374)",
        "Coefficient": 0.5,
        "Significance": "Not Significant",
        "arid": 22239288,
        "rssdid": 2239288.0,
        "Zipcode": "60090",
        "State_id": 17.0,
        "Bank_Name": "Wintrust Bank, N.A."
    },
    {
        "arid_id": 7194,
        "County": 17031,
        "T-Value": "(0.088)",
        "Coefficient": 0.022,
        "Significance": "Not Significant",
        "arid": 91007846,
        "rssdid": 1007846.0,
        "Zipcode": "60090",
        "State_id": 17.0,
        "Bank_Name": "First Midwest Bank"
    },
    {
        "arid_id": 7199,
        "County": 17031,
        "T-Value": "(0.048)",
        "Coefficient": 0.059,
        "Significance": "Not Significant",
        "arid": 91842065,
        "rssdid": 1842065.0,
        "Zipcode": "60090",
        "State_id": 17.0,
        "Bank_Name": "Cibc Bank USA"
    },
    {
        "arid_id": 7207,
        "County": 17031,
        "T-Value": "(0.119)",
        "Coefficient": -0.077,
        "Significance": "Not Significant",
        "arid": 92712969,
        "rssdid": 2712969.0,
        "Zipcode": "60090",
        "State_id": 17.0,
        "Bank_Name": "Fifth Third Mortgage Company"
    },
    {
        "arid_id": 7208,
        "County": 17031,
        "T-Value": "(0.376)",
        "Coefficient": -0.038,
        "Significance": "Not Significant",
        "arid": 92735146,
        "rssdid": 2735146.0,
        "Zipcode": "60090",
        "State_id": 17.0,
        "Bank_Name": "Tiaa, FSB"
    },
    {
        "arid_id": 7221,
        "County": 17031,
        "T-Value": "(0.113)",
        "Coefficient": 0.579,
        "Significance": "***",
        "arid": 93303298,
        "rssdid": 3303298.0,
        "Zipcode": "60090",
        "State_id": 17.0,
        "Bank_Name": "Citizens Bank, National Association"
    },
    {
        "arid_id": 7619,
        "County": 17031,
        "T-Value": "(0.041)",
        "Coefficient": 0.059,
        "Significance": "Not Significant",
        "arid": 7136131491,
        "rssdid": 3871519.0,
        "Zipcode": "60090",
        "State_id": 17.0,
        "Bank_Name": "Caliber Home Loans, INC."
    },
    {
        "arid_id": 7771,
        "County": 17031,
        "T-Value": "(0.000)",
        "Coefficient": 0.0,
        "Significance": "Not Significant",
        "arid": 7232470039,
        "rssdid": 3904891.0,
        "Zipcode": "60090",
        "State_id": 17.0,
        "Bank_Name": "Cardinal Financial Company, Limited Partnership"
    },
    {
        "arid_id": 7859,
        "County": 17031,
        "T-Value": "(0.020)",
        "Coefficient": 0.089,
        "Significance": "***",
        "arid": 7264599244,
        "rssdid": 4438209.0,
        "Zipcode": "60090",
        "State_id": 17.0,
        "Bank_Name": "Loandepot.com, LLC"
    },
    {
        "arid_id": 7912,
        "County": 17031,
        "T-Value": "(0.000)",
        "Coefficient": 0.0,
        "Significance": "Not Significant",
        "arid": 7311076317,
        "rssdid": 3837412.0,
        "Zipcode": "60090",
        "State_id": 17.0,
        "Bank_Name": "M/i Financial, LLC"
    },
    {
        "arid_id": 7957,
        "County": 17031,
        "T-Value": "(0.386)",
        "Coefficient": 0.5,
        "Significance": "Not Significant",
        "arid": 7330941669,
        "rssdid": 3897500.0,
        "Zipcode": "60090",
        "State_id": 17.0,
        "Bank_Name": "Plaza Home Mortgage, INC."
    },
    {
        "arid_id": 7981,
        "County": 17031,
        "T-Value": "(0.043)",
        "Coefficient": 0.028,
        "Significance": "Not Significant",
        "arid": 7363575871,
        "rssdid": 4438478.0,
        "Zipcode": "60090",
        "State_id": 17.0,
        "Bank_Name": "Pacor Mortgage CORP."
    },
    {
        "arid_id": 7982,
        "County": 17031,
        "T-Value": "(0.000)",
        "Coefficient": 0.0,
        "Significance": "Not Significant",
        "arid": 7363679626,
        "rssdid": 4535416.0,
        "Zipcode": "60090",
        "State_id": 17.0,
        "Bank_Name": "Chicago Financial Services, INC."
    },
    {
        "arid_id": 7985,
        "County": 17031,
        "T-Value": "(0.031)",
        "Coefficient": 0.03,
        "Significance": "Not Significant",
        "arid": 7363987946,
        "rssdid": 3954328.0,
        "Zipcode": "60090",
        "State_id": 17.0,
        "Bank_Name": "Perl Mortgage"
    },
    {
        "arid_id": 7988,
        "County": 17031,
        "T-Value": "(0.020)",
        "Coefficient": 0.001,
        "Significance": "Not Significant",
        "arid": 7364115595,
        "rssdid": 3876710.0,
        "Zipcode": "60090",
        "State_id": 17.0,
        "Bank_Name": "Draper And Kramer Mortgage CORP."
    },
    {
        "arid_id": 7989,
        "County": 17031,
        "T-Value": "(0.107)",
        "Coefficient": 0.091,
        "Significance": "Not Significant",
        "arid": 7364176531,
        "rssdid": 4325514.0,
        "Zipcode": "60090",
        "State_id": 17.0,
        "Bank_Name": "First Centennial Mortgage Corporation"
    },
    {
        "arid_id": 7991,
        "County": 17031,
        "T-Value": "(0.004)",
        "Coefficient": 0.017,
        "Significance": "***",
        "arid": 7364327855,
        "rssdid": 3870099.0,
        "Zipcode": "60090",
        "State_id": 17.0,
        "Bank_Name": "Guaranteed Rate, INC."
    },
    {
        "arid_id": 8002,
        "County": 17031,
        "T-Value": "(0.232)",
        "Coefficient": -0.5,
        "Significance": "*",
        "arid": 7371542226,
        "rssdid": 3949593.0,
        "Zipcode": "60090",
        "State_id": 17.0,
        "Bank_Name": "Newrez LLC"
    },
    {
        "arid_id": 8012,
        "County": 17031,
        "T-Value": "(0.011)",
        "Coefficient": 0.007,
        "Significance": "Not Significant",
        "arid": 7382750395,
        "rssdid": 3870651.0,
        "Zipcode": "60090",
        "State_id": 17.0,
        "Bank_Name": "United Wholesale Mortgage, LLC"
    },
    {
        "arid_id": 8043,
        "County": 17031,
        "T-Value": "(0.086)",
        "Coefficient": 0.123,
        "Significance": "Not Significant",
        "arid": 7411795868,
        "rssdid": 3861163.0,
        "Zipcode": "60090",
        "State_id": 17.0,
        "Bank_Name": "Ditech Financial LLC"
    },
    {
        "arid_id": 8060,
        "County": 17031,
        "T-Value": "(0.264)",
        "Coefficient": -0.286,
        "Significance": "Not Significant",
        "arid": 7421554181,
        "rssdid": 3851584.0,
        "Zipcode": "60090",
        "State_id": 17.0,
        "Bank_Name": "Pulte Mortgage LLC"
    },
    {
        "arid_id": 8103,
        "County": 17031,
        "T-Value": "(0.000)",
        "Coefficient": -0.333,
        "Significance": "***",
        "arid": 7461728831,
        "rssdid": 4877479.0,
        "Zipcode": "60090",
        "State_id": 17.0,
        "Bank_Name": "Mutual of Omaha Mortgage, INC."
    },
    {
        "arid_id": 8134,
        "County": 17031,
        "T-Value": "(0.135)",
        "Coefficient": -0.091,
        "Significance": "Not Significant",
        "arid": 7470873092,
        "rssdid": 4533159.0,
        "Zipcode": "60090",
        "State_id": 17.0,
        "Bank_Name": "Network Capital Funding Corporation"
    },
    {
        "arid_id": 8226,
        "County": 17031,
        "T-Value": "(0.000)",
        "Coefficient": 0.0,
        "Significance": "Not Significant",
        "arid": 7571175755,
        "rssdid": 4183602.0,
        "Zipcode": "60090",
        "State_id": 17.0,
        "Bank_Name": "Crosscountry Mortgage, LLC"
    },
    {
        "arid_id": 8402,
        "County": 17031,
        "T-Value": "(0.088)",
        "Coefficient": -0.129,
        "Significance": "Not Significant",
        "arid": 7752921540,
        "rssdid": 3845828.0,
        "Zipcode": "60090",
        "State_id": 17.0,
        "Bank_Name": "Nationstar Mortgage LLC"
    },
    {
        "arid_id": 8413,
        "County": 17031,
        "T-Value": "(0.035)",
        "Coefficient": 0.142,
        "Significance": "***",
        "arid": 7760503625,
        "rssdid": 3954355.0,
        "Zipcode": "60090",
        "State_id": 17.0,
        "Bank_Name": "Fairway Independent Mortgage Corporation"
    },
    {
        "arid_id": 8507,
        "County": 17031,
        "T-Value": "(0.054)",
        "Coefficient": -0.028,
        "Significance": "Not Significant",
        "arid": 7870788512,
        "rssdid": 3555378.0,
        "Zipcode": "60090",
        "State_id": 17.0,
        "Bank_Name": "Blueleaf Lending, LLC"
    },
    {
        "arid_id": 8577,
        "County": 17031,
        "T-Value": "(0.000)",
        "Coefficient": -0.2,
        "Significance": "***",
        "arid": 9133222578,
        "rssdid": 3378018.0,
        "Zipcode": "60090",
        "State_id": 17.0,
        "Bank_Name": "Citimortgage, INC."
    },
    {
        "arid_id": 8692,
        "County": 17031,
        "T-Value": "(0.035)",
        "Coefficient": 0.231,
        "Significance": "***",
        "arid": 9540259290,
        "rssdid": 1072246.0,
        "Zipcode": "60090",
        "State_id": 17.0,
        "Bank_Name": "Suntrust Mortgage, INC."
    },
    {
        "arid_id": 8773,
        "County": 17031,
        "T-Value": "(0.162)",
        "Coefficient": 0.5,
        "Significance": "**",
        "arid": 71257809990,
        "rssdid": 2026611.0,
        "Zipcode": "60090",
        "State_id": 17.0,
        "Bank_Name": "Crown Mortgage Company"
    },
    {
        "arid_id": 8837,
        "County": 17031,
        "T-Value": "(0.192)",
        "Coefficient": -0.138,
        "Significance": "Not Significant",
        "arid": 72317700005,
        "rssdid": 3873401.0,
        "Zipcode": "60090",
        "State_id": 17.0,
        "Bank_Name": "Phh Home Loans LLC"
    },
    {
        "arid_id": 8885,
        "County": 17031,
        "T-Value": "(0.234)",
        "Coefficient": -0.2,
        "Significance": "Not Significant",
        "arid": 77056000000,
        "rssdid": 3875179.0,
        "Zipcode": "60090",
        "State_id": 17.0,
        "Bank_Name": "Sierra Pacific Mortgage Company, INC."
    },
    {
        "arid_id": 8903,
        "County": 17031,
        "T-Value": "(0.020)",
        "Coefficient": 0.062,
        "Significance": "**",
        "arid": 77197000003,
        "rssdid": 3870679.0,
        "Zipcode": "60090",
        "State_id": 17.0,
        "Bank_Name": "Quicken Loans, LLC"
    },
    {
        "arid_id": 8932,
        "County": 17031,
        "T-Value": "(0.025)",
        "Coefficient": -0.07,
        "Significance": "**",
        "arid": 77505400005,
        "rssdid": 3875692.0,
        "Zipcode": "60090",
        "State_id": 17.0,
        "Bank_Name": "Stearns Lending, LLC"
    },
    {
        "arid_id": 8958,
        "County": 17031,
        "T-Value": "(0.064)",
        "Coefficient": 0.072,
        "Significance": "Not Significant",
        "arid": 77705300001,
        "rssdid": 3869691.0,
        "Zipcode": "60090",
        "State_id": 17.0,
        "Bank_Name": "Key Mortgage Services, INC."
    }
]