[
    {
        "arid_id": 5722,
        "County": 18019,
        "T-Value": "(0.000)",
        "Coefficient": 0.377,
        "Significance": "Not Significant",
        "arid": 568287,
        "rssdid": 461674.0,
        "Zipcode": "47111",
        "State_id": 18.0,
        "Bank_Name": "Centra Credit Union"
    },
    {
        "arid_id": 6777,
        "County": 18019,
        "T-Value": "(0.000)",
        "Coefficient": -0.888,
        "Significance": "Not Significant",
        "arid": 2785473,
        "rssdid": 785473.0,
        "Zipcode": "47111",
        "State_id": 18.0,
        "Bank_Name": "First Savings Bank"
    },
    {
        "arid_id": 6911,
        "County": 18019,
        "T-Value": "(0.000)",
        "Coefficient": 0.207,
        "Significance": "Not Significant",
        "arid": 9451965,
        "rssdid": 451965.0,
        "Zipcode": "47111",
        "State_id": 18.0,
        "Bank_Name": "Wells Fargo Bank, National Association"
    },
    {
        "arid_id": 6921,
        "County": 18019,
        "T-Value": "(0.000)",
        "Coefficient": 0.11,
        "Significance": "Not Significant",
        "arid": 9504713,
        "rssdid": 504713.0,
        "Zipcode": "47111",
        "State_id": 18.0,
        "Bank_Name": "U.S. Bank National Association"
    },
    {
        "arid_id": 6952,
        "County": 18019,
        "T-Value": "(0.000)",
        "Coefficient": 0.333,
        "Significance": "Not Significant",
        "arid": 9723112,
        "rssdid": 723112.0,
        "Zipcode": "47111",
        "State_id": 18.0,
        "Bank_Name": "Fifth Third Bank, National Association"
    },
    {
        "arid_id": 6960,
        "County": 18019,
        "T-Value": "(0.000)",
        "Coefficient": 0.25,
        "Significance": "Not Significant",
        "arid": 9817824,
        "rssdid": 817824.0,
        "Zipcode": "47111",
        "State_id": 18.0,
        "Bank_Name": "Pnc Bank, National Association"
    },
    {
        "arid_id": 6962,
        "County": 18019,
        "T-Value": "(0.000)",
        "Coefficient": -0.064,
        "Significance": "Not Significant",
        "arid": 9852218,
        "rssdid": 852218.0,
        "Zipcode": "47111",
        "State_id": 18.0,
        "Bank_Name": "Jpmorgan Chase Bank, National Association"
    },
    {
        "arid_id": 7859,
        "County": 18019,
        "T-Value": "(0.000)",
        "Coefficient": -0.5,
        "Significance": "Not Significant",
        "arid": 7264599244,
        "rssdid": 4438209.0,
        "Zipcode": "47111",
        "State_id": 18.0,
        "Bank_Name": "Loandepot.com, LLC"
    }
]