[
    {
        "arid_id": 1463,
        "arid": 111001,
        "Coefficient": 0.368,
        "T-Value": "(0.069)",
        "Significance": "***",
        "County": 40111,
        "Zipcode": "74445",
        "Bank_Name": "The First National Bank And Trust Company of Okmulgee"
    },
    {
        "arid_id": 8360,
        "arid": 7720506617,
        "Coefficient": 0.0,
        "T-Value": "(0.000)",
        "Significance": "Not Significant",
        "County": 40111,
        "Zipcode": "74445",
        "Bank_Name": "United Built Homes, L.L.C."
    }
]