[
    {
        "arid_id": 2400,
        "arid": 314209,
        "Coefficient": 0.619,
        "T-Value": "(0.255)",
        "Significance": "**",
        "County": 19113,
        "Zipcode": "52314",
        "Bank_Name": "Farmers State Bank"
    },
    {
        "arid_id": 2428,
        "arid": 314650,
        "Coefficient": -0.041,
        "T-Value": "(0.014)",
        "Significance": "**",
        "County": 19113,
        "Zipcode": "52314",
        "Bank_Name": "Hills Bank And Trust Company"
    },
    {
        "arid_id": 2789,
        "arid": 317993,
        "Coefficient": -0.25,
        "T-Value": "(0.166)",
        "Significance": "Not Significant",
        "County": 19113,
        "Zipcode": "52314",
        "Bank_Name": "Keystone Savings Bank"
    },
    {
        "arid_id": 4979,
        "arid": 560269,
        "Coefficient": 0.006,
        "T-Value": "(0.005)",
        "Significance": "Not Significant",
        "County": 19113,
        "Zipcode": "52314",
        "Bank_Name": "Greenstate Credit Union"
    },
    {
        "arid_id": 5253,
        "arid": 562969,
        "Coefficient": 0.076,
        "T-Value": "(0.031)",
        "Significance": "**",
        "County": 19113,
        "Zipcode": "52314",
        "Bank_Name": "Collins Community Credit Union"
    },
    {
        "arid_id": 5294,
        "arid": 563602,
        "Coefficient": -0.03,
        "T-Value": "(0.064)",
        "Significance": "Not Significant",
        "County": 19113,
        "Zipcode": "52314",
        "Bank_Name": "Linn Area"
    },
    {
        "arid_id": 5319,
        "arid": 564049,
        "Coefficient": -0.192,
        "T-Value": "(0.096)",
        "Significance": "*",
        "County": 19113,
        "Zipcode": "52314",
        "Bank_Name": "Dupaco Community"
    },
    {
        "arid_id": 5344,
        "arid": 564418,
        "Coefficient": -0.016,
        "T-Value": "(0.037)",
        "Significance": "Not Significant",
        "County": 19113,
        "Zipcode": "52314",
        "Bank_Name": "Veridian Credit Union"
    },
    {
        "arid_id": 6911,
        "arid": 9451965,
        "Coefficient": 0.037,
        "T-Value": "(0.025)",
        "Significance": "Not Significant",
        "County": 19113,
        "Zipcode": "52314",
        "Bank_Name": "Wells Fargo Bank, National Association"
    },
    {
        "arid_id": 6921,
        "arid": 9504713,
        "Coefficient": 0.307,
        "T-Value": "(0.177)",
        "Significance": "Not Significant",
        "County": 19113,
        "Zipcode": "52314",
        "Bank_Name": "U.S. Bank National Association"
    },
    {
        "arid_id": 7859,
        "arid": 7264599244,
        "Coefficient": 0.5,
        "T-Value": "(0.285)",
        "Significance": "Not Significant",
        "County": 19113,
        "Zipcode": "52314",
        "Bank_Name": "Loandepot.com, LLC"
    },
    {
        "arid_id": 8056,
        "arid": 7421130287,
        "Coefficient": 0.116,
        "T-Value": "(0.119)",
        "Significance": "Not Significant",
        "County": 19113,
        "Zipcode": "52314",
        "Bank_Name": "Iowa Bankers Mortgage Corporation"
    }
]