[
    {
        "arid_id": 1979,
        "arid": 125093,
        "Coefficient": 0.115,
        "T-Value": "(0.192)",
        "Significance": "Not Significant",
        "County": 26099,
        "Zipcode": "48050",
        "Bank_Name": "National Cooperative Bank, N.A."
    },
    {
        "arid_id": 5165,
        "arid": 562049,
        "Coefficient": 0.104,
        "T-Value": "(0.121)",
        "Significance": "Not Significant",
        "County": 26099,
        "Zipcode": "48050",
        "Bank_Name": "Michigan Schools And Government"
    },
    {
        "arid_id": 5961,
        "arid": 912311,
        "Coefficient": 0.115,
        "T-Value": "(0.103)",
        "Significance": "Not Significant",
        "County": 26099,
        "Zipcode": "48050",
        "Bank_Name": "The Huntington National Bank"
    },
    {
        "arid_id": 5965,
        "arid": 960143,
        "Coefficient": -0.03,
        "T-Value": "(0.051)",
        "Significance": "Not Significant",
        "County": 26099,
        "Zipcode": "48050",
        "Bank_Name": "Comerica Bank"
    },
    {
        "arid_id": 6886,
        "arid": 9146672,
        "Coefficient": 0.024,
        "T-Value": "(0.071)",
        "Significance": "Not Significant",
        "County": 26099,
        "Zipcode": "48050",
        "Bank_Name": "Flagstar Bank, FSB"
    },
    {
        "arid_id": 6911,
        "arid": 9451965,
        "Coefficient": -0.002,
        "T-Value": "(0.039)",
        "Significance": "Not Significant",
        "County": 26099,
        "Zipcode": "48050",
        "Bank_Name": "Wells Fargo Bank, National Association"
    },
    {
        "arid_id": 6914,
        "arid": 9476810,
        "Coefficient": 0.101,
        "T-Value": "(0.051)",
        "Significance": "*",
        "County": 26099,
        "Zipcode": "48050",
        "Bank_Name": "Citibank, National Association"
    },
    {
        "arid_id": 6915,
        "arid": 9480228,
        "Coefficient": -0.021,
        "T-Value": "(0.079)",
        "Significance": "Not Significant",
        "County": 26099,
        "Zipcode": "48050",
        "Bank_Name": "Bank of America, National Association"
    },
    {
        "arid_id": 6927,
        "arid": 9542649,
        "Coefficient": 0.0,
        "T-Value": "(0.000)",
        "Significance": "Not Significant",
        "County": 26099,
        "Zipcode": "48050",
        "Bank_Name": "Chemical Bank"
    },
    {
        "arid_id": 6952,
        "arid": 9723112,
        "Coefficient": -0.333,
        "T-Value": "(0.339)",
        "Significance": "Not Significant",
        "County": 26099,
        "Zipcode": "48050",
        "Bank_Name": "Fifth Third Bank, National Association"
    },
    {
        "arid_id": 6960,
        "arid": 9817824,
        "Coefficient": 1.131,
        "T-Value": "(0.170)",
        "Significance": "***",
        "County": 26099,
        "Zipcode": "48050",
        "Bank_Name": "Pnc Bank, National Association"
    },
    {
        "arid_id": 6962,
        "arid": 9852218,
        "Coefficient": 0.099,
        "T-Value": "(0.025)",
        "Significance": "***",
        "County": 26099,
        "Zipcode": "48050",
        "Bank_Name": "Jpmorgan Chase Bank, National Association"
    },
    {
        "arid_id": 7126,
        "arid": 23351440,
        "Coefficient": 0.0,
        "T-Value": "(0.000)",
        "Significance": "Not Significant",
        "County": 26099,
        "Zipcode": "48050",
        "Bank_Name": "Main Street Bank"
    },
    {
        "arid_id": 7221,
        "arid": 93303298,
        "Coefficient": 0.042,
        "T-Value": "(0.060)",
        "Significance": "Not Significant",
        "County": 26099,
        "Zipcode": "48050",
        "Bank_Name": "Citizens Bank, National Association"
    },
    {
        "arid_id": 7570,
        "arid": 5383358941,
        "Coefficient": 0.5,
        "T-Value": "(0.256)",
        "Significance": "*",
        "County": 26099,
        "Zipcode": "48050",
        "Bank_Name": "Mortgage Center L.c"
    },
    {
        "arid_id": 7619,
        "arid": 7136131491,
        "Coefficient": 0.086,
        "T-Value": "(0.064)",
        "Significance": "Not Significant",
        "County": 26099,
        "Zipcode": "48050",
        "Bank_Name": "Caliber Home Loans, INC."
    },
    {
        "arid_id": 7771,
        "arid": 7232470039,
        "Coefficient": 0.0,
        "T-Value": "(0.000)",
        "Significance": "Not Significant",
        "County": 26099,
        "Zipcode": "48050",
        "Bank_Name": "Cardinal Financial Company, Limited Partnership"
    },
    {
        "arid_id": 7848,
        "arid": 7263780954,
        "Coefficient": 0.219,
        "T-Value": "(0.187)",
        "Significance": "Not Significant",
        "County": 26099,
        "Zipcode": "48050",
        "Bank_Name": "Premia Mortgage, LLC"
    },
    {
        "arid_id": 7859,
        "arid": 7264599244,
        "Coefficient": -0.01,
        "T-Value": "(0.196)",
        "Significance": "Not Significant",
        "County": 26099,
        "Zipcode": "48050",
        "Bank_Name": "Loandepot.com, LLC"
    },
    {
        "arid_id": 8008,
        "arid": 7382434249,
        "Coefficient": 0.052,
        "T-Value": "(0.058)",
        "Significance": "Not Significant",
        "County": 26099,
        "Zipcode": "48050",
        "Bank_Name": "Towne Mortgage Company"
    },
    {
        "arid_id": 8012,
        "arid": 7382750395,
        "Coefficient": 0.024,
        "T-Value": "(0.056)",
        "Significance": "Not Significant",
        "County": 26099,
        "Zipcode": "48050",
        "Bank_Name": "United Wholesale Mortgage, LLC"
    },
    {
        "arid_id": 8023,
        "arid": 7383616059,
        "Coefficient": -0.187,
        "T-Value": "(0.149)",
        "Significance": "Not Significant",
        "County": 26099,
        "Zipcode": "48050",
        "Bank_Name": "Member First Mortgage, LLC"
    },
    {
        "arid_id": 8043,
        "arid": 7411795868,
        "Coefficient": 0.0,
        "T-Value": "(0.000)",
        "Significance": "Not Significant",
        "County": 26099,
        "Zipcode": "48050",
        "Bank_Name": "Ditech Financial LLC"
    },
    {
        "arid_id": 8060,
        "arid": 7421554181,
        "Coefficient": 0.0,
        "T-Value": "(0.000)",
        "Significance": "Not Significant",
        "County": 26099,
        "Zipcode": "48050",
        "Bank_Name": "Pulte Mortgage LLC"
    },
    {
        "arid_id": 8402,
        "arid": 7752921540,
        "Coefficient": 0.155,
        "T-Value": "(0.178)",
        "Significance": "Not Significant",
        "County": 26099,
        "Zipcode": "48050",
        "Bank_Name": "Nationstar Mortgage LLC"
    },
    {
        "arid_id": 8836,
        "arid": 72172609997,
        "Coefficient": 0.0,
        "T-Value": "(0.000)",
        "Significance": "Not Significant",
        "County": 26099,
        "Zipcode": "48050",
        "Bank_Name": "Staunton Financial, INC."
    },
    {
        "arid_id": 8903,
        "arid": 77197000003,
        "Coefficient": -0.012,
        "T-Value": "(0.032)",
        "Significance": "Not Significant",
        "County": 26099,
        "Zipcode": "48050",
        "Bank_Name": "Quicken Loans, LLC"
    },
    {
        "arid_id": 8956,
        "arid": 77687600009,
        "Coefficient": 0.002,
        "T-Value": "(0.024)",
        "Significance": "Not Significant",
        "County": 26099,
        "Zipcode": "48050",
        "Bank_Name": "Mortgage 1 Incorporated"
    },
    {
        "arid_id": 8986,
        "arid": 77983500003,
        "Coefficient": 0.667,
        "T-Value": "(0.440)",
        "Significance": "Not Significant",
        "County": 26099,
        "Zipcode": "48050",
        "Bank_Name": "Michigan Mutual, INC."
    }
]