[
    {
        "arid_id": 6963,
        "arid": 9852320,
        "Coefficient": 0.274,
        "T-Value": "(0.044)",
        "Significance": "***",
        "County": 37165,
        "Zipcode": "28351",
        "Bank_Name": "Truist Bank"
    },
    {
        "arid_id": 7196,
        "arid": 91189117,
        "Coefficient": 0.526,
        "T-Value": "(0.024)",
        "Significance": "***",
        "County": 37165,
        "Zipcode": "28351",
        "Bank_Name": "State Employees'"
    }
]