[
    {
        "arid_id": 3232,
        "arid": 326799,
        "Coefficient": -0.437,
        "T-Value": "(0.000)",
        "Significance": "***",
        "County": 1043,
        "Zipcode": "35058",
        "Bank_Name": "Evabank"
    },
    {
        "arid_id": 3943,
        "arid": 357554,
        "Coefficient": 0.0,
        "T-Value": "(0.000)",
        "Significance": "Not Significant",
        "County": 1043,
        "Zipcode": "35058",
        "Bank_Name": "Traditions Bank"
    }
]