[
    {
        "arid_id": 656,
        "arid": 35903,
        "Coefficient": -0.18,
        "T-Value": "(0.000)",
        "Significance": "***",
        "County": 28101,
        "Zipcode": "39327",
        "Bank_Name": "Bankplus"
    },
    {
        "arid_id": 6894,
        "arid": 9233031,
        "Coefficient": -0.333,
        "T-Value": "(0.000)",
        "Significance": "***",
        "County": 28101,
        "Zipcode": "39327",
        "Bank_Name": "Regions Bank"
    }
]