[{"arid_id": "1370", "arid": "1702454", "Coefficient": "0.159", "T-Value": "(0.029)", "Significance": "***", "County": "34025", "Zipcode": "07712", "Bank_Name": "Columbia Bank"}, {"arid_id": "1636", "arid": "9146672", "Coefficient": "-0.251", "T-Value": "(0.043)", "Significance": "***", "County": "34025", "Zipcode": "07712", "Bank_Name": "Flagstar Bank, Fsb"}, {"arid_id": "1652", "arid": "9451965", "Coefficient": "0.046", "T-Value": "(0.058)", "Significance": "Not Significant", "County": "34025", "Zipcode": "07712", "Bank_Name": "Wells Fargo Bank, National Association"}, {"arid_id": "1655", "arid": "9480228", "Coefficient": "-0.430", "T-Value": "(0.016)", "Significance": "***", "County": "34025", "Zipcode": "07712", "Bank_Name": "Bank Of America, National Association"}, {"arid_id": "1680", "arid": "9722777", "Coefficient": "0.060", "T-Value": "(0.089)", "Significance": "Not Significant", "County": "34025", "Zipcode": "07712", "Bank_Name": "Santander Bank, N.a."}, {"arid_id": "1688", "arid": "9817824", "Coefficient": "0.417", "T-Value": "(0.068)", "Significance": "***", "County": "34025", "Zipcode": "07712", "Bank_Name": "Pnc Bank, National Association"}, {"arid_id": "1689", "arid": "9852218", "Coefficient": "0.050", "T-Value": "(0.043)", "Significance": "Not Significant", "County": "34025", "Zipcode": "07712", "Bank_Name": "Jpmorgan Chase Bank, National Association"}, {"arid_id": "1742", "arid": "92618780", "Coefficient": "0.191", "T-Value": "(0.068)", "Significance": "**", "County": "34025", "Zipcode": "07712", "Bank_Name": "Texas Capital Bank, National Association"}, {"arid_id": "1749", "arid": "93303298", "Coefficient": "-0.574", "T-Value": "(0.064)", "Significance": "***", "County": "34025", "Zipcode": "07712", "Bank_Name": "Citizens Bank, National Association"}, {"arid_id": "1808", "arid": "3271190043", "Coefficient": "0.108", "T-Value": "(0.025)", "Significance": "***", "County": "34025", "Zipcode": "07712", "Bank_Name": "First Choice Loan Services Inc."}, {"arid_id": "1875", "arid": "7136131491", "Coefficient": "0.185", "T-Value": "(0.075)", "Significance": "**", "County": "34025", "Zipcode": "07712", "Bank_Name": "Caliber Home Loans, Inc."}, {"arid_id": "1921", "arid": "7208921389", "Coefficient": "0.117", "T-Value": "(0.075)", "Significance": "Not Significant", "County": "34025", "Zipcode": "07712", "Bank_Name": "Home Point Financial Corporation"}, {"arid_id": "1929", "arid": "7223039688", "Coefficient": "-0.170", "T-Value": "(0.044)", "Significance": "***", "County": "34025", "Zipcode": "07712", "Bank_Name": "Freedom Mortgage Corporation"}, {"arid_id": "1980", "arid": "7264599244", "Coefficient": "0.068", "T-Value": "(0.107)", "Significance": "Not Significant", "County": "34025", "Zipcode": "07712", "Bank_Name": "Loandepot.com, Llc"}, {"arid_id": "2039", "arid": "7364327855", "Coefficient": "-0.125", "T-Value": "(0.026)", "Significance": "***", "County": "34025", "Zipcode": "07712", "Bank_Name": "Guaranteed Rate, Inc."}, {"arid_id": "2046", "arid": "7371542226", "Coefficient": "0.668", "T-Value": "(0.085)", "Significance": "***", "County": "34025", "Zipcode": "07712", "Bank_Name": "Newrez Llc"}, {"arid_id": "2052", "arid": "7382750395", "Coefficient": "0.200", "T-Value": "(0.056)", "Significance": "***", "County": "34025", "Zipcode": "07712", "Bank_Name": "United Wholesale Mortgage, Llc"}, {"arid_id": "2172", "arid": "7731577221", "Coefficient": "-0.100", "T-Value": "(0.048)", "Significance": "*", "County": "34025", "Zipcode": "07712", "Bank_Name": "Gateway First Bank"}, {"arid_id": "2187", "arid": "7752921540", "Coefficient": "-0.307", "T-Value": "(0.125)", "Significance": "**", "County": "34025", "Zipcode": "07712", "Bank_Name": "Nationstar Mortgage Llc"}, {"arid_id": "2192", "arid": "7760503625", "Coefficient": "-0.138", "T-Value": "(0.052)", "Significance": "**", "County": "34025", "Zipcode": "07712", "Bank_Name": "Fairway Independent Mortgage Corporation"}, {"arid_id": "2266", "arid": "9133222578", "Coefficient": "-0.050", "T-Value": "(0.095)", "Significance": "Not Significant", "County": "34025", "Zipcode": "07712", "Bank_Name": "Citimortgage, Inc."}, {"arid_id": "2332", "arid": "73027509990", "Coefficient": "-0.142", "T-Value": "(0.075)", "Significance": "*", "County": "34025", "Zipcode": "07712", "Bank_Name": "Phh Mortgage Corporation"}, {"arid_id": "2333", "arid": "73028209994", "Coefficient": "0.093", "T-Value": "(0.071)", "Significance": "Not Significant", "County": "34025", "Zipcode": "07712", "Bank_Name": "Mortgage Access Corp."}, {"arid_id": "2356", "arid": "77197000003", "Coefficient": "-0.082", "T-Value": "(0.065)", "Significance": "Not Significant", "County": "34025", "Zipcode": "07712", "Bank_Name": "Quicken Loans, Llc"}, {"arid_id": "2367", "arid": "77505400005", "Coefficient": "-0.291", "T-Value": "(0.068)", "Significance": "***", "County": "34025", "Zipcode": "07712", "Bank_Name": "Stearns Lending, Llc"}, {"arid_id": "2388", "arid": "77810600004", "Coefficient": "-0.022", "T-Value": "(0.071)", "Significance": "Not Significant", "County": "34025", "Zipcode": "07712", "Bank_Name": "Provident Funding Associates, L.p."}, {"arid_id": "2389", "arid": "77811300008", "Coefficient": "-0.017", "T-Value": "(0.071)", "Significance": "Not Significant", "County": "34025", "Zipcode": "07712", "Bank_Name": "Homebridge Financial Services, Inc."}]