[{"arid_id": "937", "arid": "511307", "Coefficient": "-0.332", "T-Value": "(0.169)", "Significance": "*", "County": "51107", "Zipcode": "20180", "Bank_Name": "Apple Federal Credit Union"}, {"arid_id": "1636", "arid": "9146672", "Coefficient": "0.019", "T-Value": "(0.221)", "Significance": "Not Significant", "County": "51107", "Zipcode": "20180", "Bank_Name": "Flagstar Bank, Fsb"}, {"arid_id": "1652", "arid": "9451965", "Coefficient": "0.057", "T-Value": "(0.168)", "Significance": "Not Significant", "County": "51107", "Zipcode": "20180", "Bank_Name": "Wells Fargo Bank, National Association"}, {"arid_id": "1655", "arid": "9480228", "Coefficient": "-0.163", "T-Value": "(0.117)", "Significance": "Not Significant", "County": "51107", "Zipcode": "20180", "Bank_Name": "Bank Of America, National Association"}, {"arid_id": "1660", "arid": "9501105", "Coefficient": "0.371", "T-Value": "(0.063)", "Significance": "***", "County": "51107", "Zipcode": "20180", "Bank_Name": "Manufacturers And Traders Trust Company"}, {"arid_id": "1672", "arid": "9619877", "Coefficient": "-0.143", "T-Value": "(0.105)", "Significance": "Not Significant", "County": "51107", "Zipcode": "20180", "Bank_Name": "Usaa Federal Savings Bank"}, {"arid_id": "1674", "arid": "9675332", "Coefficient": "-0.020", "T-Value": "(0.086)", "Significance": "Not Significant", "County": "51107", "Zipcode": "20180", "Bank_Name": "Suntrust Banks, Inc."}, {"arid_id": "1689", "arid": "9852218", "Coefficient": "-0.172", "T-Value": "(0.028)", "Significance": "***", "County": "51107", "Zipcode": "20180", "Bank_Name": "Jpmorgan Chase Bank, National Association"}, {"arid_id": "1749", "arid": "93303298", "Coefficient": "0.016", "T-Value": "(0.032)", "Significance": "Not Significant", "County": "51107", "Zipcode": "20180", "Bank_Name": "Citizens Bank, National Association"}, {"arid_id": "1875", "arid": "7136131491", "Coefficient": "-0.256", "T-Value": "(0.126)", "Significance": "*", "County": "51107", "Zipcode": "20180", "Bank_Name": "Caliber Home Loans, Inc."}, {"arid_id": "1907", "arid": "7205216358", "Coefficient": "-0.491", "T-Value": "(0.162)", "Significance": "**", "County": "51107", "Zipcode": "20180", "Bank_Name": "Prosperity Home Mortgage, Llc"}, {"arid_id": "1980", "arid": "7264599244", "Coefficient": "-0.213", "T-Value": "(0.062)", "Significance": "***", "County": "51107", "Zipcode": "20180", "Bank_Name": "Loandepot.com, Llc"}, {"arid_id": "2039", "arid": "7364327855", "Coefficient": "0.137", "T-Value": "(0.097)", "Significance": "Not Significant", "County": "51107", "Zipcode": "20180", "Bank_Name": "Guaranteed Rate, Inc."}, {"arid_id": "2052", "arid": "7382750395", "Coefficient": "0.217", "T-Value": "(0.203)", "Significance": "Not Significant", "County": "51107", "Zipcode": "20180", "Bank_Name": "United Wholesale Mortgage, Llc"}, {"arid_id": "2068", "arid": "7412259092", "Coefficient": "0.014", "T-Value": "(0.035)", "Significance": "Not Significant", "County": "51107", "Zipcode": "20180", "Bank_Name": "Mclean Mortgage Corporation"}, {"arid_id": "2071", "arid": "7421554181", "Coefficient": "0.077", "T-Value": "(0.361)", "Significance": "Not Significant", "County": "51107", "Zipcode": "20180", "Bank_Name": "Pulte Mortgage Llc"}, {"arid_id": "2143", "arid": "7611645461", "Coefficient": "4.147", "T-Value": "(509.484)", "Significance": "Not Significant", "County": "51107", "Zipcode": "20180", "Bank_Name": "Atlantic Coast Mortgage, Llc"}, {"arid_id": "2187", "arid": "7752921540", "Coefficient": "-4.180", "T-Value": "(509.392)", "Significance": "Not Significant", "County": "51107", "Zipcode": "20180", "Bank_Name": "Nationstar Mortgage Llc"}, {"arid_id": "2192", "arid": "7760503625", "Coefficient": "-0.152", "T-Value": "(0.051)", "Significance": "**", "County": "51107", "Zipcode": "20180", "Bank_Name": "Fairway Independent Mortgage Corporation"}, {"arid_id": "2356", "arid": "77197000003", "Coefficient": "-0.050", "T-Value": "(0.013)", "Significance": "***", "County": "51107", "Zipcode": "20180", "Bank_Name": "Quicken Loans, Llc"}, {"arid_id": "2364", "arid": "77416700009", "Coefficient": "0.100", "T-Value": "(0.053)", "Significance": "*", "County": "51107", "Zipcode": "20180", "Bank_Name": "Intercoastal Mortgage Company"}, {"arid_id": "2388", "arid": "77810600004", "Coefficient": "-0.034", "T-Value": "(0.534)", "Significance": "Not Significant", "County": "51107", "Zipcode": "20180", "Bank_Name": "Provident Funding Associates, L.p."}]